AUTHORS.rst
CONTRIBUTING.rst
HISTORY.rst
LICENSE
MANIFEST.in
README.rst
setup.py
demo/manage.py
demo/demo/__init__.py
demo/demo/forms.py
demo/demo/settings.py
demo/demo/urls.py
demo/demo/views.py
demo/demo/wsgi.py
django_tvdb.egg-info/PKG-INFO
django_tvdb.egg-info/SOURCES.txt
django_tvdb.egg-info/dependency_links.txt
django_tvdb.egg-info/not-zip-safe
django_tvdb.egg-info/top_level.txt
tvdb/__init__.py
tvdb/apps.py
tvdb/forms.py
tvdb/models.py
tvdb/tests.py
tvdb/urls.py
tvdb/utils.py
tvdb/views.py
tvdb/migrations/__init__.py