Metadata-Version: 1.1
Name: django-tvdb
Version: 0.0.1
Summary: TVDB support for Django projects
Home-page: https://github.com/miigotu/django-tvdb
Author: Dustyn Gibson
Author-email: miigotu@gmail.com
License: GNU General Public License v2 (GPLv2)
Keywords: django-tvdb
Platform: UNKNOWN
Classifier: Development Status :: 1 - Planning
Classifier: Intended Audience :: Developers
Classifier: License :: OSI Approved :: GNU General Public License v2 (GPLv2)
Classifier: Programming Language :: Python :: 2
Classifier: Programming Language :: Python :: 2.7
Classifier: Programming Language :: Python :: 3
Classifier: Programming Language :: Python :: 3.3
Classifier: Programming Language :: Python :: 3.4
Classifier: Programming Language :: Python :: 3.5
Classifier: Operating System :: OS Independent
Classifier: Topic :: Software Development :: Libraries
Classifier: Topic :: Utilities
Classifier: Environment :: Web Environment
Classifier: Framework :: Django
